CHANGES.txt
COPYING.txt
MANIFEST.in
README.rst
setup.py
bin/wikitrans
testdata/bold.html
testdata/bold.texi
testdata/bold.text
testdata/bold.wiki
testdata/boldit0.html
testdata/boldit0.texi
testdata/boldit0.wiki
testdata/boldit1.html
testdata/boldit1.texi
testdata/boldit1.text
testdata/boldit1.wiki
testdata/boldit2.html
testdata/boldit2.texi
testdata/boldit2.text
testdata/boldit2.wiki
testdata/boldit3.html
testdata/boldit3.texi
testdata/boldit3.text
testdata/boldit3.wiki
testdata/colon.html
testdata/colon.texi
testdata/colon.text
testdata/colon.wiki
testdata/deflist.html
testdata/deflist.texi
testdata/deflist.text
testdata/deflist.wiki
testdata/dom.wiki
testdata/header0.texi
testdata/header0.wiki
testdata/headings.html
testdata/headings.texi
testdata/headings.text
testdata/headings.wiki
testdata/hz.html
testdata/hz.texi
testdata/hz.text
testdata/hz.wiki
testdata/it.html
testdata/it.texi
testdata/it.text
testdata/it.wiki
testdata/itbold1.html
testdata/itbold1.texi
testdata/itbold1.text
testdata/itbold1.wiki
testdata/itbold2.html
testdata/itbold2.texi
testdata/itbold2.text
testdata/itbold2.wiki
testdata/itbold3.html
testdata/itbold3.texi
testdata/itbold3.text
testdata/itbold3.wiki
testdata/link.texi
testdata/link.wiki
testdata/nowiki-ind.html
testdata/nowiki-ind.text
testdata/nowiki-ind.wiki
testdata/nowiki-tag.html
testdata/nowiki-tag.texi
testdata/nowiki-tag.text
testdata/nowiki-tag.wiki
testdata/nowiki.html
testdata/nowiki.texi
testdata/nowiki.text
testdata/nowiki.wiki
testdata/numlist.html
testdata/numlist.texi
testdata/numlist.text
testdata/numlist.wiki
testdata/para.html
testdata/para.texi
testdata/para.text
testdata/para.wiki
testdata/reclink.wiki
testdata/unlist.html
testdata/unlist.texi
testdata/unlist.text
testdata/unlist.wiki
tests/__init__.py
tests/test_html.py
tests/test_texi.py
tests/test_text.py
tests/wikitest.py
wikitrans/__init__.py
wikitrans/wiki2html.py
wikitrans/wiki2texi.py
wikitrans/wiki2text.py
wikitrans/wikidump.py
wikitrans/wikimarkup.py
wikitrans.egg-info/PKG-INFO
wikitrans.egg-info/SOURCES.txt
wikitrans.egg-info/dependency_links.txt
wikitrans.egg-info/top_level.txt