Metadata-Version: 2.1
Name: wikitrans
Version: 1.4
Summary: Wiki markup translator.
Home-page: http://www.gnu.org.ua/projects/wikitrans
Author: Sergey Poznyakoff
Author-email: gray@gnu.org
License: GPL License
Keywords: mediawiki markup translation
Platform: any
Classifier: Development Status :: 4 - Beta
Classifier: Intended Audience :: Developers
Classifier: License :: OSI Approved :: GNU General Public License (GPL)
Classifier: Operating System :: OS Independent
Classifier: Programming Language :: Python
Classifier: Topic :: Software Development :: Libraries :: Python Modules
Classifier: Topic :: Text Processing :: Markup
Requires-Python: >=3.5
